{
  "project_info": {
    "project_number": "1054392847654",
    "project_id": "personal-note-2b218",
    "storage_bucket": "personal-note-2b218.firebasestorage.app"
  },
  "client": [
    {
      "client_info": {
        "mobilesdk_app_id": "1:1054392847654:android:bc72e21aefeeec389285e7",
        "android_client_info": {
          "package_name": "com.example.personal_notes"
        }
      },
      "oauth_client": [],
      "api_key": [
        {
          "current_key": "AIzaSyBDUGkZ-bSMXTFv6pt21XnqUJmcNDwy3Yg"
        }
      ],
      "services": {
        "appinvite_service": {
          "other_platform_oauth_client": []
        }
      }
    }
  ],
  "configuration_version": "1"
}